mcp_base/__init__.py
mcp_base/add_user.py
mcp_base/cli.py
mcp_base/create_secrets.py
mcp_base/make_config.py
mcp_base/setup_auth0.py
mcp_base/setup_generic.py
mcp_base/setup_oidc.py
mcp_base/setup_rbac.py
mcp_base/py.typed
mcp_base-0.3.1.dist-info/METADATA
mcp_base-0.3.1.dist-info/WHEEL
mcp_base-0.3.1.dist-info/entry_points.txt
mcp_base-0.3.1.dist-info/licenses/LICENSE
mcp_base-0.3.1.dist-info/RECORD
