Metadata-Version: 2.4
Name: mcp-base
Version: 0.3.1
Summary: CLI tools for MCP (Model Context Protocol) server setup and management with OIDC support (Auth0, Dex, Keycloak)
Project-URL: Homepage, https://github.com/your-org/mcp-base
Project-URL: Documentation, https://github.com/your-org/mcp-base#readme
Project-URL: Repository, https://github.com/your-org/mcp-base.git
Project-URL: Issues, https://github.com/your-org/mcp-base/issues
Author: MCP Base Contributors
License-Expression: MIT
License-File: LICENSE
Keywords: auth0,cli,devops,dex,keycloak,kubernetes,mcp,model-context-protocol,oidc
Classifier: Development Status :: 4 - Beta
Classifier: Environment :: Console
Classifier: Intended Audience :: Developers
Classifier: Intended Audience :: System Administrators
Classifier: License :: OSI Approved :: MIT License
Classifier: Operating System :: OS Independent
Classifier: Programming Language :: Python :: 3
Classifier: Programming Language :: Python :: 3.9
Classifier: Programming Language :: Python :: 3.10
Classifier: Programming Language :: Python :: 3.11
Classifier: Programming Language :: Python :: 3.12
Classifier: Topic :: Software Development :: Build Tools
Classifier: Topic :: System :: Systems Administration
Requires-Python: >=3.9
Requires-Dist: requests>=2.28.0
Provides-Extra: all
Requires-Dist: cryptography>=41.0.0; extra == 'all'
Requires-Dist: kubernetes>=28.0.0; extra == 'all'
Provides-Extra: dev
Requires-Dist: black>=23.0.0; extra == 'dev'
Requires-Dist: cryptography>=41.0.0; extra == 'dev'
Requires-Dist: kubernetes>=28.0.0; extra == 'dev'
Requires-Dist: mypy>=1.0.0; extra == 'dev'
Requires-Dist: pytest-cov>=4.0.0; extra == 'dev'
Requires-Dist: pytest>=7.0.0; extra == 'dev'
Requires-Dist: ruff>=0.1.0; extra == 'dev'
Requires-Dist: types-requests>=2.28.0; extra == 'dev'
Provides-Extra: kubernetes
Requires-Dist: cryptography>=41.0.0; extra == 'kubernetes'
Requires-Dist: kubernetes>=28.0.0; extra == 'kubernetes'
